{
	"name": "LastSaturdayTrigger",
	"properties": {
		"annotations": [],
		"runtimeState": "Started",
		"pipelines": [
			{
				"pipelineReference": {
					"referenceName": "pipeline1",
					"type": "PipelineReference"
				}
			}
		],
		"type": "ScheduleTrigger",
		"typeProperties": {
			"recurrence": {
				"frequency": "Month",
				"interval": 1,
				"startTime": "2025-07-09T21:16:00",
				"timeZone": "India Standard Time",
				"schedule": {
					"minutes": [
						0
					],
					"hours": [
						3
					],
					"monthlyOccurrences": [
						{
							"day": "Saturday",
							"occurrence": -1
						}
					]
				}
			}
		}
	}
}